BlockTimer/BlockTimer.py
BlockTimer/__init__.py
blocktimer_python-0.1.6.dist-info/LICENSE
blocktimer_python-0.1.6.dist-info/METADATA
blocktimer_python-0.1.6.dist-info/WHEEL
blocktimer_python-0.1.6.dist-info/top_level.txt
blocktimer_python-0.1.6.dist-info/RECORD
